docling_parse/__init__.py
docling_parse/pdf_parser.py
docling_parse/pdf_parsers.cpython-310-x86_64-linux-gnu.so
docling_parse/performance_timings.py
docling_parse/processing_dir.py
docling_parse/processing_s3.py
docling_parse/py.typed
docling_parse/visualize.py
docling_parse/pdf_resources/cmap-resources.txt
docling_parse/pdf_resources/cmap-resources/LICENSE.md
docling_parse/pdf_resources/cmap-resources/README.md
docling_parse/pdf_resources/cmap-resources/VERSIONS.txt
docling_parse/pdf_resources/cmap-resources/Adobe-CNS1-7/cid2code.txt
docling_parse/pdf_resources/cmap-resources/Adobe-CNS1-7/CMap/Adobe-CNS1-0
docling_parse/pdf_resources/cmap-resources/Adobe-CNS1-7/CMap/Adobe-CNS1-1
docling_parse/pdf_resources/cmap-resources/Adobe-CNS1-7/CMap/Adobe-CNS1-2
docling_parse/pdf_resources/cmap-resources/Adobe-CNS1-7/CMap/Adobe-CNS1-3
docling_parse/pdf_resources/cmap-resources/Adobe-CNS1-7/CMap/Adobe-CNS1-4
docling_parse/pdf_resources/cmap-resources/Adobe-CNS1-7/CMap/Adobe-CNS1-5
docling_parse/pdf_resources/cmap-resources/Adobe-CNS1-7/CMap/Adobe-CNS1-6
docling_parse/pdf_resources/cmap-resources/Adobe-CNS1-7/CMap/Adobe-CNS1-7
docling_parse/pdf_resources/cmap-resources/Adobe-CNS1-7/CMap/B5-H
docling_parse/pdf_resources/cmap-resources/Adobe-CNS1-7/CMap/B5-V
docling_parse/pdf_resources/cmap-resources/Adobe-CNS1-7/CMap/B5pc-H
docling_parse/pdf_resources/cmap-resources/Adobe-CNS1-7/CMap/B5pc-V
docling_parse/pdf_resources/cmap-resources/Adobe-CNS1-7/CMap/CNS-EUC-H
docling_parse/pdf_resources/cmap-resources/Adobe-CNS1-7/CMap/CNS-EUC-V
docling_parse/pdf_resources/cmap-resources/Adobe-CNS1-7/CMap/CNS1-H
docling_parse/pdf_resources/cmap-resources/Adobe-CNS1-7/CMap/CNS1-V
docling_parse/pdf_resources/cmap-resources/Adobe-CNS1-7/CMap/CNS2-H
docling_parse/pdf_resources/cmap-resources/Adobe-CNS1-7/CMap/CNS2-V
docling_parse/pdf_resources/cmap-resources/Adobe-CNS1-7/CMap/ETHK-B5-H
docling_parse/pdf_resources/cmap-resources/Adobe-CNS1-7/CMap/ETHK-B5-V
docling_parse-5.2.0.dist-info/METADATA
docling_parse-5.2.0.dist-info/WHEEL
docling_parse-5.2.0.dist-info/top_level.txt
docling_parse-5.2.0.dist-info/RECORD
docling_parse-5.2.0.dist-info/licenses/LICENSE
