Metadata-Version: 2.4
Name: docling-parse
Version: 5.2.0
Summary: Simple package to extract text with coordinates from programmatic PDFs
Author-email: Peter Staar <taa@zurich.ibm.com>, Christoph Auer <cau@zurich.ibm.com>, Michele Dolfi <dol@zurich.ibm.com>, Panos Vagenas <pva@zurich.ibm.com>, Maxim Lysak <mly@zurich.ibm.com>
License-Expression: MIT
Project-URL: Homepage, https://github.com/docling-project/docling-parse
Project-URL: Repository, https://github.com/docling-project/docling-parse
Keywords: docling,pdf,parser
Classifier: Operating System :: MacOS :: MacOS X
Classifier: Operating System :: POSIX :: Linux
Classifier: Operating System :: Microsoft :: Windows
Classifier: Development Status :: 5 - Production/Stable
Classifier: Intended Audience :: Developers
Classifier: Intended Audience :: Science/Research
Classifier: Programming Language :: C++
Classifier: Programming Language :: Python :: 3
Classifier: Programming Language :: Python :: 3.10
Classifier: Programming Language :: Python :: 3.11
Classifier: Programming Language :: Python :: 3.12
Classifier: Programming Language :: Python :: 3.13
Classifier: Programming Language :: Python :: 3.14
Requires-Python: >=3.10
License-File: LICENSE
Requires-Dist: tabulate<1.0.0,>=0.9.0
Requires-Dist: pillow<13.0.0,>=10.0.0
Requires-Dist: pydantic>=2.0.0
Requires-Dist: docling-core>=2.44.1
Requires-Dist: pywin32>=305; sys_platform == "win32"
Provides-Extra: perf-tools
Requires-Dist: pdfplumber>=0.11.7; extra == "perf-tools"
Requires-Dist: pymupdf>=1.26.4; extra == "perf-tools"
Requires-Dist: pypdfium2>=4.30.0; extra == "perf-tools"
Dynamic: license-file
